pysclump/__init__.py
pysclump/sclump.py
pysclump/utils.py
pysclump/PathSim/__init__.py
pysclump/PathSim/pathsim.py
src/__init__.py
src/sclump.py
src/utils.py
src/PathSim/__init__.py
src/PathSim/pathsim.py
pysclump-0.0.4.dist-info/LICENSE
pysclump-0.0.4.dist-info/METADATA
pysclump-0.0.4.dist-info/WHEEL
pysclump-0.0.4.dist-info/top_level.txt
pysclump-0.0.4.dist-info/RECORD
