Metadata-Version: 2.1
Name: pysclump
Version: 0.0.4
Summary: SClump implemented in Python.
Home-page: https://github.com/ameya98/PySClump
Author: Ameya Daigavane
Author-email: ameya.d.98@gmail.com
License: UNKNOWN
Platform: UNKNOWN
Classifier: Programming Language :: Python :: 2
Classifier: Programming Language :: Python :: 3
Classifier: License :: OSI Approved :: MIT License
Classifier: Operating System :: OS Independent
